stringtr.py
stringtr-1.0.dist-info/METADATA
stringtr-1.0.dist-info/WHEEL
stringtr-1.0.dist-info/top_level.txt
stringtr-1.0.dist-info/RECORD
